post_slug.py
post_slug-1.0.1.dist-info/licenses/LICENSE
post_slug-1.0.1.dist-info/WHEEL
post_slug-1.0.1.dist-info/METADATA
post_slug-1.0.1.dist-info/RECORD
