Metadata-Version: 2.4
Name: post_slug
Version: 1.0.1
Summary: Cross-language slug generator for URL-safe and filename-safe strings
Author-email: Gary Dean <garydean@okusi.id>
Requires-Python: >=3.10
Classifier: License :: OSI Approved :: GNU General Public License v3 or later (GPLv3+)
Classifier: Programming Language :: Python :: 3
Classifier: Programming Language :: Python :: 3.10
Classifier: Programming Language :: Python :: 3.11
Classifier: Programming Language :: Python :: 3.12
License-File: LICENSE
Project-URL: Home, https://github.com/Open-Technology-Foundation/post_slug
